nbsearch/__init__.py
nbsearch/cli.py
nbsearch/nbsearch.py
nbsearch/nbwatchdog.py
nbsearch/static/clipboard.min.js
nbsearch/static/marked.min.js
nbsearch/static/nbsearch.css
nbsearch/static/prism.css
nbsearch/static/prism.js
nbsearch/templates/index.html
nbsearch-0.0.4.dist-info/LICENSE
nbsearch-0.0.4.dist-info/METADATA
nbsearch-0.0.4.dist-info/WHEEL
nbsearch-0.0.4.dist-info/entry_points.txt
nbsearch-0.0.4.dist-info/top_level.txt
nbsearch-0.0.4.dist-info/RECORD
