Metadata-Version: 2.1
Name: nbsearch
Version: 0.0.4
Summary: datasette powered notebook search
Home-page: https://github.com/ouseful-testing/nbsearch
Author: Tony Hirst
Author-email: tony.hirst@open.ac.uk
License: MIT License
Platform: UNKNOWN
Classifier: Development Status :: 3 - Alpha
Classifier: Environment :: Web Environment
Classifier: Intended Audience :: Education
Classifier: License :: Free For Educational Use
Classifier: Programming Language :: Python :: 3.6
Classifier: Programming Language :: Python :: 3.7
Classifier: Topic :: Education
Requires-Dist: sqlite-utils
Requires-Dist: nbformat
Requires-Dist: datasette (>=0.51a0)
Requires-Dist: jupytext
Requires-Dist: watchdog
Requires-Dist: jupyter-server-proxy
Requires-Dist: click
Requires-Dist: nb-quality-profile
